{
  "Id": 2,
  "Name": "Wizard",
  "Selectable": true,
  "MaleSprites": [
    1,
    2,
    3,
    4,
    5
  ],
  "FemaleSprites": [
    1,
    2,
    3,
    4,
    5
  ],
  "GenderLock": false,
  "Gender": 0,
  "Level": 1,
  "Experience": 0,
  "AttributePoint": 5,
  "AttributePointPerLevel": 5,
  "MapId": 1,
  "X": 10,
  "Y": 10,
  "Vital": {
    "HP": 100,
    "MP": 100,
    "Special": 0
  },
  "Primary": {
    "Strength": 15,
    "Agility": 16,
    "Constitution": 17,
    "Intelligence": 18,
    "Spirit": 19,
    "Will": 20
  },
  "Secondary": {
    "Attack": 150,
    "Defense": 0,
    "Accuracy": 0,
    "Evasion": 0,
    "Parry": 0,
    "Block": 0,
    "MagicAttack": 0,
    "MagicDefense": 0,
    "MagicAccuracy": 0,
    "MagicResist": 0,
    "Concentration": 0,
    "SilenceResistance": 0,
    "BlindResistance": 0,
    "StunResistance": 0,
    "StumbleResistance": 0
  },
  "Unique": {
    "CritRate": 0.1,
    "CritDamage": 0.1,
    "ResistCritRate": 0,
    "ResistCritDamage": 0,
    "HealingPower": 0,
    "FinalDamage": 0,
    "Amplification": 0,
    "DamageSuppression": 0,
    "Enmity": 0,
    "AttackSpeed": 0,
    "CastSpeed": 0,
    "PveAttack": 0,
    "PveDefense": 0,
    "PvpAttack": 0,
    "PvpDefense": 0
  },
  "ElementAttack": {
    "Neutral": 0,
    "Fire": 0,
    "Water": 0,
    "Earth": 0,
    "Wind": 0,
    "Light": 0,
    "Dark": 0
  },
  "ElementDefense": {
    "Neutral": 0,
    "Fire": 0,
    "Water": 0,
    "Earth": 0,
    "Wind": 0,
    "Light": 0,
    "Dark": 0
  },
  "VitalGrowth": {
    "HP": {
      "Attributes": {
        "Level": 100,
        "Strength": 1,
        "Agility": 1,
        "Constitution": 1,
        "Intelligence": 1,
        "Spirit": 1,
        "Will": 1
      }
    },
    "MP": {
      "Attributes": {
        "Level": 100,
        "Strength": 1,
        "Agility": 1,
        "Constitution": 1,
        "Intelligence": 1,
        "Spirit": 1,
        "Will": 1
      }
    },
    "Special": {
      "Attributes": {
        "Level": 100,
        "Strength": 1,
        "Agility": 1,
        "Constitution": 1,
        "Intelligence": 1,
        "Spirit": 1,
        "Will": 1
      }
    }
  },
  "SecondaryGrowth": {
    "Attack": {
      "Attributes": {
        "Level": 1,
        "Strength": 5,
        "Agility": 5,
        "Constitution": 5,
        "Intelligence": 5,
        "Spirit": 5,
        "Will": 5
      }
    },
    "Defense": {
      "Attributes": {
        "Level": 1,
        "Strength": 5,
        "Agility": 5,
        "Constitution": 5,
        "Intelligence": 5,
        "Spirit": 5,
        "Will": 5
      }
    },
    "Accuracy": {
      "Attributes": {
        "Level": 1,
        "Strength": 5,
        "Agility": 5,
        "Constitution": 5,
        "Intelligence": 5,
        "Spirit": 5,
        "Will": 5
      }
    },
    "Evasion": {
      "Attributes": {
        "Level": 1,
        "Strength": 5,
        "Agility": 5,
        "Constitution": 5,
        "Intelligence": 5,
        "Spirit": 5,
        "Will": 5
      }
    },
    "Parry": {
      "Attributes": {
        "Level": 1,
        "Strength": 5,
        "Agility": 5,
        "Constitution": 5,
        "Intelligence": 5,
        "Spirit": 5,
        "Will": 5
      }
    },
    "Block": {
      "Attributes": {
        "Level": 0,
        "Strength": 0,
        "Agility": 0,
        "Constitution": 0,
        "Intelligence": 0,
        "Spirit": 0,
        "Will": 0
      }
    },
    "MagicAttack": {
      "Attributes": {
        "Level": 0,
        "Strength": 0,
        "Agility": 0,
        "Constitution": 0,
        "Intelligence": 0,
        "Spirit": 0,
        "Will": 0
      }
    },
    "MagicDefense": {
      "Attributes": {
        "Level": 0,
        "Strength": 0,
        "Agility": 0,
        "Constitution": 0,
        "Intelligence": 0,
        "Spirit": 0,
        "Will": 0
      }
    },
    "MagicAccuracy": {
      "Attributes": {
        "Level": 0,
        "Strength": 0,
        "Agility": 0,
        "Constitution": 0,
        "Intelligence": 0,
        "Spirit": 0,
        "Will": 0
      }
    },
    "MagicResist": {
      "Attributes": {
        "Level": 0,
        "Strength": 0,
        "Agility": 0,
        "Constitution": 0,
        "Intelligence": 0,
        "Spirit": 0,
        "Will": 0
      }
    },
    "Concentration": {
      "Attributes": {
        "Level": 0,
        "Strength": 0,
        "Agility": 0,
        "Constitution": 0,
        "Intelligence": 0,
        "Spirit": 0,
        "Will": 0
      }
    },
    "SilenceResistance": {
      "Attributes": {
        "Level": 0,
        "Strength": 0,
        "Agility": 0,
        "Constitution": 0,
        "Intelligence": 0,
        "Spirit": 0,
        "Will": 0
      }
    },
    "BlindResistance": {
      "Attributes": {
        "Level": 0,
        "Strength": 0,
        "Agility": 0,
        "Constitution": 0,
        "Intelligence": 0,
        "Spirit": 0,
        "Will": 0
      }
    },
    "StunResistance": {
      "Attributes": {
        "Level": 0,
        "Strength": 0,
        "Agility": 0,
        "Constitution": 0,
        "Intelligence": 0,
        "Spirit": 0,
        "Will": 0
      }
    },
    "StumbleResistance": {
      "Attributes": {
        "Level": 0,
        "Strength": 0,
        "Agility": 0,
        "Constitution": 0,
        "Intelligence": 0,
        "Spirit": 0,
        "Will": 0
      }
    }
  },
  "UniqueGrowth": {
    "CritRate": {
      "Attributes": {
        "Level": 0,
        "Strength": 0,
        "Agility": 0,
        "Constitution": 0,
        "Intelligence": 0,
        "Spirit": 0,
        "Will": 0
      }
    },
    "CritDamage": {
      "Attributes": {
        "Level": 0,
        "Strength": 0,
        "Agility": 0,
        "Constitution": 0,
        "Intelligence": 0,
        "Spirit": 0,
        "Will": 0
      }
    },
    "ResistCritRate": {
      "Attributes": {
        "Level": 0,
        "Strength": 0,
        "Agility": 0,
        "Constitution": 0,
        "Intelligence": 0,
        "Spirit": 0,
        "Will": 0
      }
    },
    "ResistCritDamage": {
      "Attributes": {
        "Level": 0,
        "Strength": 0,
        "Agility": 0,
        "Constitution": 0,
        "Intelligence": 0,
        "Spirit": 0,
        "Will": 0
      }
    },
    "HealingPower": {
      "Attributes": {
        "Level": 0,
        "Strength": 0,
        "Agility": 0,
        "Constitution": 0,
        "Intelligence": 0,
        "Spirit": 0,
        "Will": 0
      }
    },
    "FinalDamage": {
      "Attributes": {
        "Level": 0,
        "Strength": 0,
        "Agility": 0,
        "Constitution": 0,
        "Intelligence": 0,
        "Spirit": 0,
        "Will": 0
      }
    },
    "Amplification": {
      "Attributes": {
        "Level": 0,
        "Strength": 0,
        "Agility": 0,
        "Constitution": 0,
        "Intelligence": 0,
        "Spirit": 0,
        "Will": 0
      }
    },
    "DamageSuppression": {
      "Attributes": {
        "Level": 0,
        "Strength": 0,
        "Agility": 0,
        "Constitution": 0,
        "Intelligence": 0,
        "Spirit": 0,
        "Will": 0
      }
    },
    "Enmity": {
      "Attributes": {
        "Level": 0,
        "Strength": 0,
        "Agility": 0,
        "Constitution": 0,
        "Intelligence": 0,
        "Spirit": 0,
        "Will": 0
      }
    },
    "AttackSpeed": {
      "Attributes": {
        "Level": 0,
        "Strength": 0,
        "Agility": 0,
        "Constitution": 0,
        "Intelligence": 0,
        "Spirit": 0,
        "Will": 0
      }
    },
    "CastSpeed": {
      "Attributes": {
        "Level": 0,
        "Strength": 0,
        "Agility": 0,
        "Constitution": 0,
        "Intelligence": 0,
        "Spirit": 0,
        "Will": 0
      }
    },
    "PveAttack": {
      "Attributes": {
        "Level": 0,
        "Strength": 0,
        "Agility": 0,
        "Constitution": 0,
        "Intelligence": 0,
        "Spirit": 0,
        "Will": 0
      }
    },
    "PveDefense": {
      "Attributes": {
        "Level": 0,
        "Strength": 0,
        "Agility": 0,
        "Constitution": 0,
        "Intelligence": 0,
        "Spirit": 0,
        "Will": 0
      }
    },
    "PvpAttack": {
      "Attributes": {
        "Level": 0,
        "Strength": 0,
        "Agility": 0,
        "Constitution": 0,
        "Intelligence": 0,
        "Spirit": 0,
        "Will": 0
      }
    },
    "PvpDefense": {
      "Attributes": {
        "Level": 0,
        "Strength": 0,
        "Agility": 0,
        "Constitution": 0,
        "Intelligence": 0,
        "Spirit": 0,
        "Will": 0
      }
    }
  },
  "Skills": [
    {
      "Id": 1,
      "Level": 1
    }
  ],
  "Passives": [
    {
      "Id": 1,
      "Level": 1
    }
  ],
  "Inventories": [
    {
      "Id": 1,
      "Value": 1,
      "Level": 1,
      "AttributeId": 0,
      "UpgradeId": 0,
      "Bound": false
    }
  ],
  "Equipments": [
    {
      "Id": 0
    }
  ]
}